amplitude/__init__.py
amplitude/test_amplitude.py
amplitude_python-0.12.dist-info/DESCRIPTION.rst
amplitude_python-0.12.dist-info/METADATA
amplitude_python-0.12.dist-info/RECORD
amplitude_python-0.12.dist-info/WHEEL
amplitude_python-0.12.dist-info/metadata.json
amplitude_python-0.12.dist-info/top_level.txt
