Metadata-Version: 2.0
Name: amplitude-python
Version: 0.12
Summary: UNKNOWN
Home-page: https://github.com/atveit/amplitude-python
Author: Amund Tveit
Author-email: atveit@gmail.com
License: Apache License 2.0
Keywords: python wrapper for amplitude.com HTTP API
Platform: UNKNOWN
Classifier: Development Status :: 3 - Alpha
Classifier: Intended Audience :: Developers
Classifier: Topic :: System :: Logging
Classifier: License :: OSI Approved :: Apache Software License
Classifier: Programming Language :: Python :: 3.6
Requires-Dist: requests
Requires-Dist: nose
Requires-Dist: requests-mock[fixture]
Requires-Dist: testtools
Requires-Dist: twine
